openvela/__init__.py
openvela/__main__.py
openvela/agents.py
openvela/cli.py
openvela/completion.py
openvela/files.py
openvela/llms.py
openvela/logs.py
openvela/memory.py
openvela/messages.py
openvela/runner.py
openvela/server.py
openvela/tasks.py
openvela/tools.py
openvela/workflows.py
openvela-0.4.6.dist-info/LICENSE
openvela-0.4.6.dist-info/METADATA
openvela-0.4.6.dist-info/WHEEL
openvela-0.4.6.dist-info/entry_points.txt
openvela-0.4.6.dist-info/RECORD
