Metadata-Version: 2.3
Name: openvela
Version: 0.4.6
Summary: 
Author: Joel Zamboni
Author-email: joel.zamboni@webera.com
Requires-Python: >=3.9,<4.0
Classifier: Programming Language :: Python :: 3
Classifier: Programming Language :: Python :: 3.9
Classifier: Programming Language :: Python :: 3.10
Classifier: Programming Language :: Python :: 3.11
Classifier: Programming Language :: Python :: 3.12
Classifier: Programming Language :: Python :: 3.13
Requires-Dist: fastapi (>=0.115.4,<0.116.0)
Requires-Dist: groq (>=0.11.0,<0.12.0)
Requires-Dist: ollama (>=0.3.3,<0.4.0)
Requires-Dist: openai (>=1.52.1,<2.0.0)
Requires-Dist: pillow (>=11.0.0,<12.0.0)
Requires-Dist: requests (>=2.32.3,<3.0.0)
Requires-Dist: sqlalchemy (>=2.0.37,<3.0.0)
Requires-Dist: uvicorn (>=0.32.0,<0.33.0)
